plotml/__init__.py
plotml/sklearn.py
plotml-0.2.4.dist-info/LICENSE.txt
plotml-0.2.4.dist-info/METADATA
plotml-0.2.4.dist-info/WHEEL
plotml-0.2.4.dist-info/top_level.txt
plotml-0.2.4.dist-info/RECORD
