Metadata-Version: 2.1
Name: plotml
Version: 0.2.4
Summary: Some neat plotting functions for ML
Home-page: https://github.com/pschrempf/plotml
Author: Patrick Schrempf
Author-email: pschrempf@outlook.com
License: MIT
Download-URL: https://github.com/pschrempf/plotml/archive/0.2.tar.gz
Keywords: plot,machine-learning
Platform: UNKNOWN
Classifier: Development Status :: 3 - Alpha
Classifier: Intended Audience :: Developers
Classifier: Topic :: Software Development :: Build Tools
Classifier: License :: OSI Approved :: MIT License
Classifier: Programming Language :: Python :: 3.6
Requires-Dist: numpy
Requires-Dist: matplotlib
